phototoscan/__init__.py
phototoscan/__main__.py
phototoscan/py.typed
phototoscan/scanner.py
phototoscan/document_scanner/__init__.py
phototoscan/document_scanner/scan.py
phototoscan/pyimagesearch/__init__.py
phototoscan/pyimagesearch/imutils.py
phototoscan/pyimagesearch/transform.py
phototoscan-0.1.5.dist-info/METADATA
phototoscan-0.1.5.dist-info/WHEEL
phototoscan-0.1.5.dist-info/entry_points.txt
phototoscan-0.1.5.dist-info/RECORD
