Metadata-Version: 2.4
Name: phototoscan
Version: 0.1.5
Summary: A Python library that converts casual document snapshots into professional-quality scanned documents.
Project-URL: Homepage, https://github.com/j-about/PhotoToScan
Project-URL: Issues, https://github.com/j-about/PhotoToScan/issues
Author-email: j-about <142051449+j-about@users.noreply.github.com>, Andrew Campbell <andrewc@captricity.com>, joaofauvel <fauvel@tutanota.com>
Classifier: Development Status :: 4 - Beta
Classifier: Programming Language :: Python :: 3
Classifier: Programming Language :: Python :: 3 :: Only
Classifier: Programming Language :: Python :: 3.8
Classifier: Programming Language :: Python :: 3.9
Classifier: Programming Language :: Python :: 3.10
Classifier: Programming Language :: Python :: 3.11
Classifier: Programming Language :: Python :: 3.12
Classifier: Programming Language :: Python :: 3.13
Classifier: Topic :: Multimedia :: Graphics :: Capture :: Scanners
Classifier: Topic :: Scientific/Engineering :: Image Processing
Classifier: Topic :: Software Development :: Libraries :: Python Modules
Requires-Python: >=3.8
Requires-Dist: numpy<2.0.0,>=1.18.5
Requires-Dist: ocrd-fork-pylsd<=0.0.8,>=0.0.3
Requires-Dist: opencv-python<=5.0.0.0,>=4.2.0.34
Requires-Dist: puremagic<2.0,>=1.29
Requires-Dist: scipy<2.0,>=1.5
